SBVisualizer/.DS_Store
SBVisualizer/Visualizer.py
SBVisualizer/__init__.py
SBVisualizer-0.1.3.dist-info/LICENSE
SBVisualizer-0.1.3.dist-info/METADATA
SBVisualizer-0.1.3.dist-info/WHEEL
SBVisualizer-0.1.3.dist-info/top_level.txt
SBVisualizer-0.1.3.dist-info/RECORD
