Metadata-Version: 2.1
Name: SBVisualizer
Version: 0.1.3
Summary: Visualizer for SBMLDiagrams
Author: Priyanka Talur
Author-email: ptalur@uw.edu
Classifier: Programming Language :: Python :: 3
Classifier: License :: OSI Approved :: MIT License
Classifier: Operating System :: OS Independent
License-File: LICENSE
Requires-Dist: tellurium
Requires-Dist: SBMLDiagrams
